{"tasks":[{"title":"Front","description":"Estudar Front","id":"0a7c4713-dbef-4af2-91bc-0f95dcb43bd1","create_at":"2023-08-29T14:40:13.149Z","updated_at":"2023-08-29T14:42:01.015Z","completed_at":"2023-08-29T14:42:01.015Z"},{"title":"Hadouken","description":"shoryuken","id":"ec54d82a-1831-469e-bcad-4828b2c4bd8d","create_at":"2023-08-29T14:40:13.610Z","updated_at":"2023-08-29T14:51:30.239Z","completed_at":"2023-08-29T14:44:02.776Z"},{"title":"Front","description":"Estudar Front","id":"04d96f55-bd04-46de-9c58-e54cf945059d","create_at":"2023-08-29T14:40:14.283Z","updated_at":"2023-08-29T14:40:14.283Z","completed_at":null},{"title":"Front","description":"Estudar Front","id":"80f7e5a7-4f9b-4fab-a0bb-dda360fd8e74","create_at":"2023-08-29T14:40:15.357Z","updated_at":"2023-08-29T14:40:15.357Z","completed_at":null},{"title":"Task 01","description":"Descrição da Task 01","id":"56ee4fa3-25f1-44c0-9740-82e66522bf66","created_at":"2023-08-29T15:15:15.446Z","updated_at":"2023-08-29T15:15:15.446Z","completed_at":null},{"title":"Task 02","description":"Descrição da Task 02","id":"b53f70ed-962b-4ae1-b27f-8f07da2c0e00","created_at":"2023-08-29T15:15:15.451Z","updated_at":"2023-08-29T15:15:15.451Z","completed_at":null},{"title":"Task 03","description":"Descrição da Task 03","id":"03aa2ee4-e561-4eb1-b0b5-1e930632ed75","created_at":"2023-08-29T15:15:15.453Z","updated_at":"2023-08-29T15:15:15.453Z","completed_at":null},{"title":"Task 04","description":"Descrição da Task 04","id":"ecabcb81-5d8d-480d-80fa-381443f915cf","created_at":"2023-08-29T15:15:15.455Z","updated_at":"2023-08-29T15:15:15.455Z","completed_at":null},{"title":"Task 05","description":"Descrição da Task 05","id":"7b8835bd-0f68-45f3-a9e9-7fb2af2d6943","created_at":"2023-08-29T15:15:15.456Z","updated_at":"2023-08-29T15:15:15.456Z","completed_at":null}]}